sintegra-ie-validator/__init__.py
sintegra-ie-validator/acre.py
sintegra-ie-validator/alagoas.py
sintegra-ie-validator/base.py
sintegra-ie-validator/goias.py
sintegra-ie-validator/mato_grosso.py
sintegra-ie-validator/minas_gerais.py
sintegra-ie-validator/pernambuco.py
sintegra-ie-validator/sao_paulo.py
sintegraIEValidator/__init__.py
sintegraIEValidator/acre.py
sintegraIEValidator/alagoas.py
sintegraIEValidator/base.py
sintegraIEValidator/goias.py
sintegraIEValidator/mato_grosso.py
sintegraIEValidator/minas_gerais.py
sintegraIEValidator/pernambuco.py
sintegraIEValidator/sao_paulo.py
sintegraIEValidator-0.1.6.dist-info/LICENSE
sintegraIEValidator-0.1.6.dist-info/METADATA
sintegraIEValidator-0.1.6.dist-info/WHEEL
sintegraIEValidator-0.1.6.dist-info/top_level.txt
sintegraIEValidator-0.1.6.dist-info/RECORD
