Metadata-Version: 2.1
Name: sintegraIEValidator
Version: 0.1.6
Summary: Um validador de inscrição estadual para estados brasileiros.
Home-page: https://github.com/josetiagobispo/sintegra-ie-validator
Author: Seu Nome
Author-email: seuemail@example.com
License: MIT
Keywords: validação inscrição estadual brasil estados
Classifier: Development Status :: 3 - Alpha
Classifier: Intended Audience :: Developers
Classifier: Topic :: Software Development :: Libraries :: Python Modules
Classifier: License :: OSI Approved :: MIT License
Classifier: Programming Language :: Python :: 3
Classifier: Programming Language :: Python :: 3.11
License-File: LICENSE
